storage/__init__.py
universal_storage-0.0.1.dist-info/LICENSE
universal_storage-0.0.1.dist-info/METADATA
universal_storage-0.0.1.dist-info/WHEEL
universal_storage-0.0.1.dist-info/top_level.txt
universal_storage-0.0.1.dist-info/RECORD
