Metadata-Version: 2.1
Name: universal-storage
Version: 0.0.1
Summary: An util for python backend storage packaging.
Home-page: UNKNOWN
Author: df_coding
Author-email: df_coding@163.com
License: UNKNOWN
Keywords: storage
Platform: UNKNOWN
